mutate/__init__.py
mutate/infer.py
mutate/parsers/__init__.py
mutate/parsers/parser.py
mutate/parsers/text_classification.py
mutate/pipelines/__init__.py
mutate/pipelines/text_classification.py
mutate/prompt_datasets/__init__.py
mutate/prompt_datasets/templates.py
mutate/prompt_datasets/text_classification.py
mutate/prompt_datasets/utils.py
mutate_nlp-0.1.2.dist-info/WHEEL
mutate_nlp-0.1.2.dist-info/METADATA
mutate_nlp-0.1.2.dist-info/RECORD
