Metadata-Version: 2.1
Name: mutate-nlp
Version: 0.1.2
Summary: Text data synthesize and pseudo labelling using LLMs
License: Apache
Author: Logesh Kumar Umapathi
Author-email: logeshkumaru@gmail.com
Requires-Python: >=3.8,<4.0
Classifier: License :: Other/Proprietary License
Classifier: Programming Language :: Python :: 3
Classifier: Programming Language :: Python :: 3.8
Classifier: Programming Language :: Python :: 3.9
Classifier: Programming Language :: Python :: 3.10
Requires-Dist: Jinja2 (>=3.0.3)
Requires-Dist: datasets (>=1.6.2)
Requires-Dist: numpy (>=1.24.1,<2.0.0)
Requires-Dist: pandas (>=1.5.2,<2.0.0)
Requires-Dist: torch (>=1.0)
Requires-Dist: tqdm (>=4.64.1,<5.0.0)
Requires-Dist: transformers (>=4.5.1)
